pymeepo/__init__.py
pymeepo/agents/__init__.py
pymeepo/memory/__init__.py
pymeepo/providers/__init__.py
pymeepo/pymeepo/__init__.py
pymeepo/tools/__init__.py
pymeepo/utils/__init__.py
pymeepo-0.1.0.dist-info/LICENSE
pymeepo-0.1.0.dist-info/METADATA
pymeepo-0.1.0.dist-info/WHEEL
pymeepo-0.1.0.dist-info/RECORD
