Metadata-Version: 2.3
Name: pymeepo
Version: 0.1.0
Summary: A lightweight Python SDK for building AI agents, enabling collaborative and supervisor-worker models for complex workflows
License: GPL-3.0-only
Author: MeepoLabs
Author-email: info@meepolabs.com
Requires-Python: >=3.10,<4.0
Classifier: Development Status :: 3 - Alpha
Classifier: Intended Audience :: Developers
Classifier: License :: OSI Approved :: GNU General Public License v3 (GPLv3)
Classifier: Programming Language :: Python :: 3
Classifier: Programming Language :: Python :: 3.10
Classifier: Programming Language :: Python :: 3.11
Classifier: Programming Language :: Python :: 3.12
Classifier: Programming Language :: Python :: 3.13
Classifier: Topic :: Scientific/Engineering :: Artificial Intelligence
Classifier: Topic :: Software Development :: Libraries :: Python Modules
Requires-Dist: anthropic (>=0.8.0,<0.9.0)
Requires-Dist: httpx (>=0.25.0,<0.26.0)
Requires-Dist: litellm (>=1.0.0,<2.0.0)
Requires-Dist: openai (>=1.3.0,<2.0.0)
Requires-Dist: pydantic (>=2.5.0,<3.0.0)
Requires-Dist: tenacity (>=8.2.0,<9.0.0)
Requires-Dist: typing-extensions (>=4.8.0,<5.0.0)
Project-URL: Documentation, https://pymeepo.readthedocs.io
Project-URL: Repository, https://github.com/meepolabs/pymeepo
